mne_rsa/__init__.py
mne_rsa/folds.py
mne_rsa/rdm.py
mne_rsa/rsa.py
mne_rsa/searchlight.py
mne_rsa/sensor_level.py
mne_rsa/source_level.py
mne_rsa/viz.py
mne_rsa-1.0.dist-info/licenses/LICENSE
mne_rsa-1.0.dist-info/METADATA
mne_rsa-1.0.dist-info/WHEEL
mne_rsa-1.0.dist-info/top_level.txt
mne_rsa-1.0.dist-info/RECORD
