Metadata-Version: 2.4
Name: mne-rsa
Version: 1.0
Summary: Code for performing Representational Similarity Analysis on MNE-Python data structures.
Author-email: Marijn van Vliet <w.m.vanvliet@gmail.com>
License-Expression: BSD-3-Clause
Project-URL: Homepage, https://mne.tools/mne-rsa
Project-URL: Bug Tracker, https://github.com/mne-tools/mne-rsa/issues/
Project-URL: Source Code, https://github.com/mne-tools/mne-rsa
Keywords: rsa,meg,eeg,neuroimaging,mne-python
Classifier: Intended Audience :: Science/Research
Classifier: Intended Audience :: Developers
Classifier: Programming Language :: Python
Classifier: Topic :: Software Development
Classifier: Topic :: Scientific/Engineering
Classifier: Operating System :: Microsoft :: Windows
Classifier: Operating System :: POSIX
Classifier: Operating System :: Unix
Classifier: Operating System :: MacOS
Requires-Python: >=3.7
License-File: LICENSE
Requires-Dist: mne
Requires-Dist: nibabel
Requires-Dist: scikit-learn
Requires-Dist: pyvista
Requires-Dist: pyside6
Requires-Dist: pyvistaqt
Dynamic: license-file
